parallelbar/__init__.py
parallelbar/parallelbar.py
parallelbar/tools.py
parallelbar/wrappers.py
parallelbar-2.5.dist-info/LICENSE
parallelbar-2.5.dist-info/METADATA
parallelbar-2.5.dist-info/WHEEL
parallelbar-2.5.dist-info/top_level.txt
parallelbar-2.5.dist-info/RECORD
