Metadata-Version: 2.2
Name: parallelbar
Version: 2.5
Summary: Parallel processing with progress bars
Home-page: https://github.com/dubovikmaster/parallelbar
Author: Dubovik Pavel
Author-email: geometryk@gmail.com
License: MIT
Keywords: progress bar,tqdm,parallelbar,parallel tqdm,parallel map,parallel,multiprocessing bar
Platform: any
License-File: LICENSE
Requires-Dist: tqdm
Requires-Dist: colorama
Provides-Extra: dill
Requires-Dist: dill; extra == "dill"
Dynamic: author
Dynamic: author-email
Dynamic: description
Dynamic: description-content-type
Dynamic: home-page
Dynamic: keywords
Dynamic: license
Dynamic: platform
Dynamic: provides-extra
Dynamic: requires-dist
Dynamic: summary
